<?xml version="1.0" encoding="EUC-KR"?>
<RexMetaInfo>
<PlateInfo>
<Rect>1083,652,236,122</Rect>
<Code>전남88바1730</Code>
<LocalCode value="전남">
<Rect>1150,675,23,23</Rect>
<Rect>1176,674,23,24</Rect>
</LocalCode>
<TypeCode value="88">
<Rect>1209,673,20,26</Rect>
<Rect>1232,671,21,27</Rect>
</TypeCode>
<UseCode value="바">
<Rect>1108,706,35,38</Rect>
</UseCode>
<DigitCode value="1730">
<Rect>1153,705,30,49</Rect>
<Rect>1187,705,35,48</Rect>
<Rect>1223,705,33,47</Rect>
<Rect>1261,703,32,49</Rect>
</DigitCode>
</PlateInfo>
</RexMetaInfo>
